rpkimancer/__init__.py
rpkimancer/algorithms.py
rpkimancer/cms.py
rpkimancer/py.typed
rpkimancer/resources.py
rpkimancer/utils.py
rpkimancer/asn1/__init__.py
rpkimancer/asn1/types.py
rpkimancer/asn1/mod/__init__.py
rpkimancer/asn1/mod/__main__.py
rpkimancer/asn1/mod/modules/rfc3779/IPAddrAndASCertExtn.asn
rpkimancer/asn1/mod/modules/rfc5280/PKIX1Explicit88.asn
rpkimancer/asn1/mod/modules/rfc5280/PKIX1Implicit88.asn
rpkimancer/asn1/mod/modules/rfc5911/AlgorithmInformation-2009.asn
rpkimancer/asn1/mod/modules/rfc5911/AttributeCertificateVersion1-2009.asn
rpkimancer/asn1/mod/modules/rfc5911/CMS-AES-CCM-and-AES-GCM-2009.asn
rpkimancer/asn1/mod/modules/rfc5911/CMS-AuthEnvelopedData-2009.asn
rpkimancer/asn1/mod/modules/rfc5911/CMSAesRsaesOaep-2009.asn
rpkimancer/asn1/mod/modules/rfc5911/CMSFirmwareWrapper-2009.asn
rpkimancer/asn1/mod/modules/rfc5911/CryptographicMessageSyntax-2009.asn
rpkimancer/asn1/mod/modules/rfc5911/CryptographicMessageSyntaxAlgorithms-2009.asn
rpkimancer/asn1/mod/modules/rfc5911/ERS.asn
rpkimancer/asn1/mod/modules/rfc5911/EnrollmentMessageSyntax-2009.asn
rpkimancer/asn1/mod/modules/rfc5911/ExtendedSecurityServices-2009.asn
rpkimancer/asn1/mod/modules/rfc5911/PKIX-CommonTypes-2009.asn
rpkimancer/asn1/mod/modules/rfc5911/PKIX-X400Address-2009.asn
rpkimancer/asn1/mod/modules/rfc5911/PKIX1-PSS-OAEP-Algorithms-2009.asn
rpkimancer/asn1/mod/modules/rfc5911/PKIX1Explicit-2009.asn
rpkimancer/asn1/mod/modules/rfc5911/PKIX1Implicit-2009.asn
rpkimancer/asn1/mod/modules/rfc5911/PKIXAlgs-2009.asn
rpkimancer/asn1/mod/modules/rfc5911/PKIXAttributeCertificate-2009.asn
rpkimancer/asn1/mod/modules/rfc5911/PKIXCRMF-2009.asn
rpkimancer/asn1/mod/modules/rfc5911/SMIMESymmetricKeyDistribution-2009.asn
rpkimancer/asn1/mod/modules/rfc5911/SecureMimeMessageV3dot1-2009.asn
rpkimancer/asn1/mod/modules/rfc6268/BinarySigningTimeModule-2010.asn
rpkimancer/asn1/mod/modules/rfc6268/CMS-AuthEnvelopedData-2010.asn
rpkimancer/asn1/mod/modules/rfc6268/CompressedDataContent-2010.asn
rpkimancer-0.2.2.dist-info/LICENSE
rpkimancer-0.2.2.dist-info/METADATA
rpkimancer-0.2.2.dist-info/WHEEL
rpkimancer-0.2.2.dist-info/entry_points.txt
rpkimancer-0.2.2.dist-info/top_level.txt
rpkimancer-0.2.2.dist-info/RECORD
