Metadata-Version: 2.1
Name: rpkimancer
Version: 0.2.2
Summary: A tool for performing RPKI incantations
Home-page: https://github.com/benmaddison/rpkimancer
Author: Ben Maddison
Author-email: benm@workonline.africa
License: MIT
Project-URL: Documentation, https://benmaddison.github.io/rpkimancer
Project-URL: Bug Tracker, https://github.com/benmaddison/rpkimancer/issues
Keywords: rpki
Classifier: Development Status :: 4 - Beta
Classifier: Environment :: Console
Classifier: Intended Audience :: Developers
Classifier: Intended Audience :: Telecommunications Industry
Classifier: Natural Language :: English
Classifier: License :: OSI Approved :: MIT License
Classifier: Programming Language :: Python :: 3
Classifier: Programming Language :: Python :: 3.8
Classifier: Programming Language :: Python :: 3.9
Classifier: Programming Language :: Python :: 3.10
Classifier: Topic :: Internet
Classifier: Topic :: Security :: Cryptography
Classifier: Topic :: Software Development :: Testing
Classifier: Typing :: Typed
Requires-Python: >=3.8
License-File: LICENSE
Requires-Dist: argcomplete (<2.0,>=1.12.2)
Requires-Dist: cryptography (<38.0,>=3.4.4)
Requires-Dist: pycrate (<0.6,>=0.5.2)
